mso4000.py
mso4000-0.2.0.dist-info/licenses/LICENSE
mso4000-0.2.0.dist-info/METADATA
mso4000-0.2.0.dist-info/WHEEL
mso4000-0.2.0.dist-info/top_level.txt
mso4000-0.2.0.dist-info/RECORD
