Metadata-Version: 2.4
Name: mso4000
Version: 0.2.0
Summary: Simple library for Tektronix MSO4000 series oscilloscopes with correct time axis calculation and raw data capture
Author-email: Asaf Ayalon <ayalon.asaf.c0@s.mail.nagoya-u.ac.jp>
License-Expression: MIT
Keywords: oscilloscope,tektronix,mso4000,visa,measurement
Classifier: Development Status :: 3 - Alpha
Classifier: Intended Audience :: Science/Research
Classifier: Programming Language :: Python :: 3
Classifier: Programming Language :: Python :: 3.6
Classifier: Programming Language :: Python :: 3.7
Classifier: Programming Language :: Python :: 3.8
Classifier: Programming Language :: Python :: 3.9
Classifier: Programming Language :: Python :: 3.10
Classifier: Programming Language :: Python :: 3.11
Classifier: Topic :: Scientific/Engineering
Classifier: Topic :: Scientific/Engineering :: Physics
Requires-Python: >=3.6
License-File: LICENSE
Requires-Dist: pyvisa>=1.11.0
Requires-Dist: numpy>=1.16.0
Provides-Extra: dev
Requires-Dist: setuptools; extra == "dev"
Requires-Dist: wheel; extra == "dev"
Requires-Dist: twine; extra == "dev"
Dynamic: license-file
